egoio/__init__.py
egoio/db_tables/__init__.py
egoio/db_tables/boundaries.py
egoio/db_tables/climate.py
egoio/db_tables/demand.py
egoio/db_tables/economy.py
egoio/db_tables/emission.py
egoio/db_tables/environment.py
egoio/db_tables/grid.py
egoio/db_tables/model_draft.py
egoio/db_tables/openstreetmap.py
egoio/db_tables/reference.py
egoio/db_tables/scenario.py
egoio/db_tables/society.py
egoio/db_tables/supply.py
egoio/tools/__init__.py
egoio/tools/config.py
egoio/tools/db.py
egoio-0.4.8.dist-info/LICENSE
egoio-0.4.8.dist-info/METADATA
egoio-0.4.8.dist-info/WHEEL
egoio-0.4.8.dist-info/top_level.txt
egoio-0.4.8.dist-info/RECORD
